{
    "objects": [
        {
            "data": [
                [
                    366.0,
                    484.0
                ],
                [
                    384.85876812635615,
                    479.8316411281214
                ],
                [
                    400.6868361262532,
                    468.7636415654597
                ],
                [
                    411.0745241284999,
                    452.48100391376397
                ],
                [
                    414.44040079938077,
                    433.4626121530273
                ],
                [
                    410.2720419275024,
                    414.6038440266709
                ],
                [
                    399.20404236484046,
                    398.7757760267741
                ],
                [
                    382.9214047131445,
                    388.38808802452763
                ],
                [
                    363.90301295240806,
                    385.0222113536465
                ],
                [
                    345.0442448260519,
                    389.1905702255251
                ],
                [
                    329.2161768261549,
                    400.25856978818683
                ],
                [
                    318.8284888239082,
                    416.54120743988256
                ],
                [
                    315.4626121530273,
                    435.55959920061923
                ],
                [
                    319.63097102490565,
                    454.4183673269756
                ],
                [
                    330.6989705875676,
                    470.2464353268724
                ],
                [
                    346.98160823926355,
                    480.6341233291191
                ]
            ],
            "tags": [
                "mirror ball"
            ],
            "type": "region"
        }
    ],
    "size": [
        2592,
        1728
    ]
}