{
    "objects": [
        {
            "data": [
                [
                    410.0,
                    467.0
                ],
                [
                    428.76773736861605,
                    463.35273815808955
                ],
                [
                    444.71111911463095,
                    452.8010054386907
                ],
                [
                    455.40290989433015,
                    436.95120749663647
                ],
                [
                    459.215381482828,
                    418.2163323898285
                ],
                [
                    455.56811964091776,
                    399.44859502121244
                ],
                [
                    445.0163869215189,
                    383.5052132751973
                ],
                [
                    429.16658897946445,
                    372.81342249549857
                ],
                [
                    410.4317138726565,
                    369.0009509070005
                ],
                [
                    391.6639765040404,
                    372.64821274891096
                ],
                [
                    375.7205947580255,
                    383.1999454683098
                ],
                [
                    365.0288039783263,
                    399.04974341036404
                ],
                [
                    361.2163323898285,
                    417.784618517172
                ],
                [
                    364.8635942317387,
                    436.5523558857881
                ],
                [
                    375.41532695113756,
                    452.4957376318032
                ],
                [
                    391.265124893192,
                    463.18752841150194
                ]
            ],
            "tags": [
                "mirror ball"
            ],
            "type": "region"
        }
    ],
    "size": [
        2592,
        1728
    ]
}