{
    "objects": [
        {
            "data": [
                [
                    425.0,
                    427.0
                ],
                [
                    409.0,
                    429.0
                ],
                [
                    396.0,
                    438.0
                ],
                [
                    381.0,
                    461.0
                ],
                [
                    375.0,
                    480.0
                ],
                [
                    377.0,
                    496.0
                ],
                [
                    385.0,
                    516.0
                ],
                [
                    395.0,
                    526.0
                ],
                [
                    411.0,
                    535.0
                ],
                [
                    425.0,
                    539.0
                ],
                [
                    441.0,
                    538.0
                ],
                [
                    457.0,
                    529.0
                ],
                [
                    467.0,
                    520.0
                ],
                [
                    479.0,
                    500.0
                ],
                [
                    484.0,
                    480.0
                ],
                [
                    486.0,
                    463.0
                ],
                [
                    478.0,
                    447.0
                ],
                [
                    460.0,
                    434.0
                ],
                [
                    448.0,
                    426.0
                ],
                [
                    426.0,
                    425.0
                ]
            ],
            "tags": [
                "mirror ball"
            ],
            "type": "region"
        }
    ],
    "size": [
        2592,
        1728
    ]
}