{
    "objects": [
        {
            "data": [
                [
                    404.0,
                    508.0
                ],
                [
                    423.1177319898675,
                    504.1122421619689
                ],
                [
                    439.2924327696801,
                    493.2043829711333
                ],
                [
                    450.0616507697391,
                    476.9370451093082
                ],
                [
                    453.78587017274003,
                    457.78678330217167
                ],
                [
                    449.8981123347089,
                    438.6690513123044
                ],
                [
                    438.9902531438738,
                    422.4943505324918
                ],
                [
                    422.7229152820487,
                    411.7251325324323
                ],
                [
                    403.57265347491193,
                    408.0009131294314
                ],
                [
                    384.45492148504445,
                    411.88867096746253
                ],
                [
                    368.28022070523184,
                    422.7965301582981
                ],
                [
                    357.5110027051728,
                    439.063868020123
                ],
                [
                    353.7867833021719,
                    458.21412982725974
                ],
                [
                    357.674541140203,
                    477.331861817127
                ],
                [
                    368.5824003310381,
                    493.5065625969396
                ],
                [
                    384.84973819286324,
                    504.2757805969991
                ]
            ],
            "tags": [
                "mirror ball"
            ],
            "type": "region"
        }
    ],
    "size": [
        2592,
        1728
    ]
}