{
    "objects": [
        {
            "data": [
                [
                    393.0,
                    398.0
                ],
                [
                    369.0,
                    403.0
                ],
                [
                    350.0,
                    423.0
                ],
                [
                    339.0,
                    448.0
                ],
                [
                    342.0,
                    480.0
                ],
                [
                    358.0,
                    499.0
                ],
                [
                    375.0,
                    504.0
                ],
                [
                    395.0,
                    503.0
                ],
                [
                    418.0,
                    499.0
                ],
                [
                    435.0,
                    483.0
                ],
                [
                    446.0,
                    462.0
                ],
                [
                    446.0,
                    431.0
                ],
                [
                    436.0,
                    417.0
                ],
                [
                    422.0,
                    400.0
                ]
            ],
            "tags": [
                "mirror ball"
            ],
            "type": "region"
        }
    ],
    "size": [
        2592,
        1728
    ]
}