{
    "objects": [
        {
            "data": [
                [
                    411.0,
                    546.0
                ],
                [
                    430.1430056789459,
                    543.4360802461297
                ],
                [
                    446.8476672047518,
                    533.7416161435242
                ],
                [
                    458.57085128824656,
                    518.3925019712692
                ],
                [
                    463.52780942364825,
                    499.7255012220239
                ],
                [
                    460.9638896697779,
                    480.58249554307804
                ],
                [
                    451.2694255671722,
                    463.87783401727233
                ],
                [
                    435.920311394917,
                    452.1546499337769
                ],
                [
                    417.2533106456722,
                    447.1976917983757
                ],
                [
                    398.1103049667263,
                    449.761611552246
                ],
                [
                    381.40564344092036,
                    459.4560756548515
                ],
                [
                    369.6824593574256,
                    474.80518982710646
                ],
                [
                    364.7255012220239,
                    493.47219057635175
                ],
                [
                    367.28942097589425,
                    512.6151962552976
                ],
                [
                    376.98388507849995,
                    529.3198577811033
                ],
                [
                    392.33299925075517,
                    541.0430418645988
                ]
            ],
            "tags": [
                "mirror ball"
            ],
            "type": "region"
        }
    ],
    "size": [
        2592,
        1728
    ]
}