{
    "objects": [
        {
            "data": [
                [
                    383.0,
                    447.0
                ],
                [
                    401.7836217302106,
                    443.4354467913679
                ],
                [
                    417.7733299364586,
                    432.9540482034008
                ],
                [
                    428.53483649140935,
                    417.15150215700214
                ],
                [
                    432.42979957537136,
                    398.433603037299
                ],
                [
                    428.86524636673903,
                    379.64998130708864
                ],
                [
                    418.3838477787717,
                    363.6602731008402
                ],
                [
                    402.58130173237305,
                    352.89876654588966
                ],
                [
                    383.86340261267014,
                    349.0038034619279
                ],
                [
                    365.07978088245954,
                    352.56835667056
                ],
                [
                    349.09007267621155,
                    363.04975525852706
                ],
                [
                    338.3285661212608,
                    378.85230130492573
                ],
                [
                    334.4336030372988,
                    397.57020042462887
                ],
                [
                    337.9981562459311,
                    416.35382215483924
                ],
                [
                    348.4795548338984,
                    432.3435303610877
                ],
                [
                    364.2821008802971,
                    443.1050369160382
                ]
            ],
            "tags": [
                "mirror ball"
            ],
            "type": "region"
        }
    ],
    "size": [
        2592,
        1728
    ]
}