{
    "objects": [
        {
            "data": [
                [
                    353.0,
                    521.0
                ],
                [
                    372.03354929939314,
                    517.7209220814348
                ],
                [
                    388.36340713527716,
                    507.40762513098093
                ],
                [
                    399.50350068267016,
                    491.6302151190753
                ],
                [
                    403.7578516841795,
                    472.7906596974526
                ],
                [
                    400.4787737656143,
                    453.7571103980599
                ],
                [
                    390.1654768151602,
                    437.4272525621752
                ],
                [
                    374.3880668032548,
                    426.2871590147829
                ],
                [
                    355.5485113816321,
                    422.0328080132731
                ],
                [
                    336.514962082239,
                    425.31188593183833
                ],
                [
                    320.18510424635497,
                    435.62518288229217
                ],
                [
                    309.04501069896196,
                    451.4025928941978
                ],
                [
                    304.7906596974526,
                    470.2421483158205
                ],
                [
                    308.06973761601785,
                    489.2756976152132
                ],
                [
                    318.3830345664719,
                    505.60555545109787
                ],
                [
                    334.16044457837734,
                    516.7456489984902
                ]
            ],
            "tags": [
                "mirror ball"
            ],
            "type": "region"
        }
    ],
    "size": [
        2592,
        1728
    ]
}