{
    "objects": [
        {
            "data": [
                [
                    382.0,
                    467.0
                ],
                [
                    390.0,
                    467.0
                ],
                [
                    403.0,
                    469.0
                ],
                [
                    412.0,
                    464.0
                ],
                [
                    421.0,
                    456.0
                ],
                [
                    427.0,
                    448.0
                ],
                [
                    435.0,
                    430.0
                ],
                [
                    435.0,
                    420.0
                ],
                [
                    432.0,
                    405.0
                ],
                [
                    421.0,
                    393.0
                ],
                [
                    413.0,
                    386.0
                ],
                [
                    406.0,
                    379.0
                ],
                [
                    394.0,
                    368.0
                ],
                [
                    373.0,
                    370.0
                ],
                [
                    363.0,
                    373.0
                ],
                [
                    350.0,
                    379.0
                ],
                [
                    341.0,
                    394.0
                ],
                [
                    337.0,
                    410.0
                ],
                [
                    333.0,
                    428.0
                ],
                [
                    337.0,
                    442.0
                ],
                [
                    345.0,
                    458.0
                ],
                [
                    366.0,
                    468.0
                ]
            ],
            "tags": [
                "mirror ball"
            ],
            "type": "region"
        }
    ],
    "size": [
        2592,
        1728
    ]
}