{
    "objects": [
        {
            "data": [
                [
                    317.0,
                    376.0
                ],
                [
                    295.0,
                    370.0
                ],
                [
                    275.0,
                    369.0
                ],
                [
                    254.0,
                    376.0
                ],
                [
                    243.0,
                    396.0
                ],
                [
                    242.0,
                    418.0
                ],
                [
                    254.0,
                    441.0
                ],
                [
                    262.0,
                    452.0
                ],
                [
                    270.0,
                    455.0
                ],
                [
                    287.0,
                    456.0
                ],
                [
                    306.0,
                    452.0
                ],
                [
                    317.0,
                    438.0
                ],
                [
                    327.0,
                    427.0
                ],
                [
                    328.0,
                    404.0
                ]
            ],
            "tags": [
                "mirror ball"
            ],
            "type": "region"
        }
    ],
    "size": [
        2592,
        1728
    ]
}