{
    "objects": [
        {
            "data": [
                [
                    369.0,
                    501.0
                ],
                [
                    359.0,
                    505.0
                ],
                [
                    349.0,
                    508.0
                ],
                [
                    340.0,
                    518.0
                ],
                [
                    332.0,
                    538.0
                ],
                [
                    334.0,
                    556.0
                ],
                [
                    344.0,
                    573.0
                ],
                [
                    365.0,
                    579.0
                ],
                [
                    381.0,
                    578.0
                ],
                [
                    396.0,
                    571.0
                ],
                [
                    404.0,
                    562.0
                ],
                [
                    411.0,
                    544.0
                ],
                [
                    408.0,
                    527.0
                ],
                [
                    395.0,
                    510.0
                ]
            ],
            "tags": [
                "mirror ball"
            ],
            "type": "region"
        }
    ],
    "size": [
        2592,
        1728
    ]
}