{
    "objects": [
        {
            "data": [
                [
                    349.0,
                    523.0
                ],
                [
                    364.0069108934872,
                    518.7130288782382
                ],
                [
                    376.2309358908751,
                    509.0094878324592
                ],
                [
                    383.81107799737356,
                    495.36665302406345
                ],
                [
                    385.59332929142784,
                    479.8615223800243
                ],
                [
                    381.3063581696665,
                    464.8546114865371
                ],
                [
                    371.6028171238868,
                    452.63058648914944
                ],
                [
                    357.95998231549174,
                    445.05044438265077
                ],
                [
                    342.45485167145216,
                    443.2681930885965
                ],
                [
                    327.44794077796496,
                    447.55516421035827
                ],
                [
                    315.22391578057704,
                    457.2587052561373
                ],
                [
                    307.6437736740786,
                    470.90154006453304
                ],
                [
                    305.8615223800243,
                    486.40667070857216
                ],
                [
                    310.14849350178565,
                    501.41358160205937
                ],
                [
                    319.8520345475654,
                    513.637606599447
                ],
                [
                    333.4948693559604,
                    521.217748705946
                ]
            ],
            "tags": [
                "mirror ball"
            ],
            "type": "region"
        }
    ],
    "size": [
        2592,
        1728
    ]
}