{
    "objects": [
        {
            "data": [
                [
                    399.0,
                    532.0
                ],
                [
                    415.1920850880724,
                    528.4220719258763
                ],
                [
                    428.7824072934627,
                    518.9200547107446
                ],
                [
                    437.70196325697725,
                    504.94054433960855
                ],
                [
                    440.59283143914763,
                    488.6117945418962
                ],
                [
                    437.0149033650241,
                    472.419709453824
                ],
                [
                    427.51288614989244,
                    458.82938724843393
                ],
                [
                    413.53337577875664,
                    449.90983128491894
                ],
                [
                    397.20462598104405,
                    447.01896310274833
                ],
                [
                    381.01254089297163,
                    450.5968911768721
                ],
                [
                    367.42221868758133,
                    460.09890839200375
                ],
                [
                    358.5026627240668,
                    474.0784187631398
                ],
                [
                    355.6117945418964,
                    490.40716856085214
                ],
                [
                    359.18972261601994,
                    506.59925364892433
                ],
                [
                    368.6917398311516,
                    520.1895758543146
                ],
                [
                    382.67125020228787,
                    529.1091318178294
                ]
            ],
            "tags": [
                "mirror ball"
            ],
            "type": "region"
        }
    ],
    "size": [
        2592,
        1728
    ]
}